{
  "name": "TpJobseekerProfile",
  "plural": "tpJobseekerProfiles",
  "base": "PersistedModel",
  "idInjection": true,
  "options": {
    "validateUpsert": true
  },
  "properties": {
    "firstName": {
      "type": "string"
    },
    "lastName": {
      "type": "string"
    },
    "createdAt": {
      "type": "date"
    }
  },
  "validations": [],
  "relations": {
    "redUser": {
      "type": "belongsTo",
      "model": "RedUser",
      "foreignKey": "",
      "options": {
        "nestRemoting": true
      }
    }
  },
  "acls": [
    {
      "accessType": "*",
      "principalType": "ROLE",
      "principalId": "$everyone",
      "permission": "DENY"
    },
    {
      "accessType": "READ",
      "principalType": "ROLE",
      "principalId": "admin",
      "permission": "ALLOW"
    }
  ],
  "methods": {}
}
